[
    {
        "Username": "dominik",
        "Password": "dominik",
        "Name": "Dominik",
        "Surname": "Figiel",
        "PhotoURL": "https://randomuser.me/api/portraits/men/3.jpg"
    },
    {
        "Username": "martin",
        "Password": "martin",
        "Name": "Martin",
        "Surname": "Haładyn",
        "PhotoURL": "https://randomuser.me/api/portraits/men/29.jpg"
    },
    {
        "Username": "marcin",
        "Password": "marcin",
        "Name": "Marcin",
        "Surname": "Rubach",
        "PhotoURL": "https://randomuser.me/api/portraits/men/83.jpg"
    },
    {
        "Username": "radek",
        "Password": "radek",
        "Name": "Radosław",
        "Surname": "Ziemniak",
        "PhotoURL": "https://randomuser.me/api/portraits/men/85.jpg"
    }
  ]